pdf_splitter/__init__.py
pdf_splitter/pdf_splitter.py
pdf_splitter-0.1.0.dist-info/AUTHORS.rst
pdf_splitter-0.1.0.dist-info/LICENSE
pdf_splitter-0.1.0.dist-info/METADATA
pdf_splitter-0.1.0.dist-info/WHEEL
pdf_splitter-0.1.0.dist-info/top_level.txt
pdf_splitter-0.1.0.dist-info/RECORD
