Metadata-Version: 2.1
Name: pdf-splitter
Version: 0.1.0
Summary: Split a PDF file by page ranges or extract all PDF pages to multiple PDF files
Home-page: https://github.com/santoshray02/pdf_splitter
Author: Santosh Ray
Author-email: rayskumar02@gmail.com
License: MIT license
Keywords: pdf_splitter
Platform: UNKNOWN
Classifier: Development Status :: 2 - Pre-Alpha
Classifier: Intended Audience :: Developers
Classifier: License :: OSI Approved :: MIT License
Classifier: Natural Language :: English
Classifier: Programming Language :: Python :: 2
Classifier: Programming Language :: Python :: 2.7
Classifier: Programming Language :: Python :: 3
Classifier: Programming Language :: Python :: 3.4
Classifier: Programming Language :: Python :: 3.5
Classifier: Programming Language :: Python :: 3.6
Classifier: Programming Language :: Python :: 3.7
Requires-Dist: PyPDF2 (>=1.26.0)
